gerrit_clone/__init__.py
gerrit_clone/cli.py
gerrit_clone/clone_manager.py
gerrit_clone/concurrent_utils.py
gerrit_clone/config.py
gerrit_clone/discovery.py
gerrit_clone/error_codes.py
gerrit_clone/file_logging.py
gerrit_clone/gerrit_api.py
gerrit_clone/git_comparison.py
gerrit_clone/git_utils.py
gerrit_clone/github_api.py
gerrit_clone/github_discovery.py
gerrit_clone/github_worker.py
gerrit_clone/logging.py
gerrit_clone/mirror_manager.py
gerrit_clone/models.py
gerrit_clone/pathing.py
gerrit_clone/progress.py
gerrit_clone/py.typed
gerrit_clone/refresh_manager.py
gerrit_clone/refresh_worker.py
gerrit_clone/reset_manager.py
gerrit_clone/reset_models.py
gerrit_clone/retry.py
gerrit_clone/rich_status.py
gerrit_clone/ssh_discovery.py
gerrit_clone/unified_discovery.py
gerrit_clone/worker.py
gerrit_clone-0.1.14.dist-info/METADATA
gerrit_clone-0.1.14.dist-info/WHEEL
gerrit_clone-0.1.14.dist-info/entry_points.txt
gerrit_clone-0.1.14.dist-info/RECORD
