Metadata-Version: 2.4
Name: gerrit-clone
Version: 0.1.14
Summary: A multi-threaded CLI tool for bulk cloning repositories from Gerrit servers
Project-URL: Homepage, https://github.com/lfreleng-actions/gerrit-clone-action
Project-URL: Documentation, https://github.com/lfreleng-actions/gerrit-clone-action#readme
Project-URL: Repository, https://github.com/lfreleng-actions/gerrit-clone-action.git
Project-URL: Issues, https://github.com/lfreleng-actions/gerrit-clone-action/issues
Project-URL: Changelog, https://github.com/lfreleng-actions/gerrit-clone-action/releases
Author-email: Matthew Watkins <mwatkins@linuxfoundation.org>
Maintainer-email: Matthew Watkins <mwatkins@linuxfoundation.org>
License-Expression: Apache-2.0
Keywords: bulk,ci-cd,clone,gerrit,git,multi-threaded,repository,ssh
Classifier: Development Status :: 4 - Beta
Classifier: Environment :: Console
Classifier: Intended Audience :: Developers
Classifier: Intended Audience :: System Administrators
Classifier: License :: OSI Approved :: Apache Software License
Classifier: Operating System :: OS Independent
Classifier: Programming Language :: Python :: 3
Classifier: Programming Language :: Python :: 3 :: Only
Classifier: Programming Language :: Python :: 3.11
Classifier: Programming Language :: Python :: 3.12
Classifier: Programming Language :: Python :: 3.13
Classifier: Topic :: Software Development :: Version Control :: Git
Classifier: Topic :: System :: Systems Administration
Classifier: Topic :: Utilities
Requires-Python: <3.14,>=3.11
Requires-Dist: httpx<0.29.0,>=0.28.1
Requires-Dist: pyyaml<7.0.0,>=6.0.3
Requires-Dist: rich<15.0.0,>=14.2.0
Requires-Dist: typer<0.22.0,>=0.21.1
Provides-Extra: dev
Requires-Dist: pytest-asyncio<1.4.0,>=0.25.3; extra == 'dev'
Requires-Dist: pytest-cov<8.0.0,>=6.3.0; extra == 'dev'
Requires-Dist: pytest-mock<4.0.0,>=3.15.1; extra == 'dev'
Requires-Dist: pytest<9.0.0,>=8.4.2; extra == 'dev'
Requires-Dist: types-pyyaml<7.0.0,>=6.0.12.20250915; extra == 'dev'
